[
  {
    "name": "Application Start",
    "start": 1586523635064,
    "end": 1586523638122,
    "duration": 3058,
    "pid": 9084,
    "index": 0
  },
  {
    "name": "Load Plugin",
    "start": 1586523635075,
    "end": 1586523635164,
    "duration": 89,
    "pid": 9084,
    "index": 1
  },
  {
    "name": "Load Config",
    "start": 1586523635164,
    "end": 1586523635241,
    "duration": 77,
    "pid": 9084,
    "index": 2
  },
  {
    "name": "Require(0) config/config.default.js",
    "start": 1586523635166,
    "end": 1586523635167,
    "duration": 1,
    "pid": 9084,
    "index": 3
  },
  {
    "name": "Require(1) node_modules/egg-session/config/config.default.js",
    "start": 1586523635172,
    "end": 1586523635172,
    "duration": 0,
    "pid": 9084,
    "index": 4
  },
  {
    "name": "Require(2) node_modules/egg-security/config/config.default.js",
    "start": 1586523635174,
    "end": 1586523635174,
    "duration": 0,
    "pid": 9084,
    "index": 5
  },
  {
    "name": "Require(3) node_modules/egg-jsonp/config/config.default.js",
    "start": 1586523635177,
    "end": 1586523635177,
    "duration": 0,
    "pid": 9084,
    "index": 6
  },
  {
    "name": "Require(4) node_modules/egg-onerror/config/config.default.js",
    "start": 1586523635179,
    "end": 1586523635180,
    "duration": 1,
    "pid": 9084,
    "index": 7
  },
  {
    "name": "Require(5) node_modules/egg-i18n/config/config.default.js",
    "start": 1586523635182,
    "end": 1586523635183,
    "duration": 1,
    "pid": 9084,
    "index": 8
  },
  {
    "name": "Require(6) node_modules/egg-watcher/config/config.default.js",
    "start": 1586523635184,
    "end": 1586523635185,
    "duration": 1,
    "pid": 9084,
    "index": 9
  },
  {
    "name": "Require(7) node_modules/egg-schedule/config/config.default.js",
    "start": 1586523635188,
    "end": 1586523635189,
    "duration": 1,
    "pid": 9084,
    "index": 10
  },
  {
    "name": "Require(8) node_modules/egg-multipart/config/config.default.js",
    "start": 1586523635191,
    "end": 1586523635192,
    "duration": 1,
    "pid": 9084,
    "index": 11
  },
  {
    "name": "Require(9) node_modules/egg-development/config/config.default.js",
    "start": 1586523635193,
    "end": 1586523635194,
    "duration": 1,
    "pid": 9084,
    "index": 12
  },
  {
    "name": "Require(10) node_modules/egg-logrotator/config/config.default.js",
    "start": 1586523635196,
    "end": 1586523635197,
    "duration": 1,
    "pid": 9084,
    "index": 13
  },
  {
    "name": "Require(11) node_modules/egg-static/config/config.default.js",
    "start": 1586523635198,
    "end": 1586523635202,
    "duration": 4,
    "pid": 9084,
    "index": 14
  },
  {
    "name": "Require(12) node_modules/egg-view/config/config.default.js",
    "start": 1586523635206,
    "end": 1586523635206,
    "duration": 0,
    "pid": 9084,
    "index": 15
  },
  {
    "name": "Require(13) node_modules/egg-view-ejs/config/config.default.js",
    "start": 1586523635208,
    "end": 1586523635209,
    "duration": 1,
    "pid": 9084,
    "index": 16
  },
  {
    "name": "Require(14) node_modules/egg-mongoose/config/config.default.js",
    "start": 1586523635211,
    "end": 1586523635212,
    "duration": 1,
    "pid": 9084,
    "index": 17
  },
  {
    "name": "Require(15) node_modules/egg-jwt/config/config.default.js",
    "start": 1586523635214,
    "end": 1586523635214,
    "duration": 0,
    "pid": 9084,
    "index": 18
  },
  {
    "name": "Require(16) node_modules/egg-cors/config/config.default.js",
    "start": 1586523635216,
    "end": 1586523635217,
    "duration": 1,
    "pid": 9084,
    "index": 19
  },
  {
    "name": "Require(17) node_modules/egg/config/config.default.js",
    "start": 1586523635218,
    "end": 1586523635219,
    "duration": 1,
    "pid": 9084,
    "index": 20
  },
  {
    "name": "Require(18) config/config.default.js",
    "start": 1586523635221,
    "end": 1586523635221,
    "duration": 0,
    "pid": 9084,
    "index": 21
  },
  {
    "name": "Require(19) node_modules/egg-security/config/config.local.js",
    "start": 1586523635224,
    "end": 1586523635224,
    "duration": 0,
    "pid": 9084,
    "index": 22
  },
  {
    "name": "Require(20) node_modules/egg-watcher/config/config.local.js",
    "start": 1586523635228,
    "end": 1586523635229,
    "duration": 1,
    "pid": 9084,
    "index": 23
  },
  {
    "name": "Require(21) node_modules/egg-view/config/config.local.js",
    "start": 1586523635234,
    "end": 1586523635234,
    "duration": 0,
    "pid": 9084,
    "index": 24
  },
  {
    "name": "Require(22) node_modules/egg-view-ejs/config/config.local.js",
    "start": 1586523635235,
    "end": 1586523635236,
    "duration": 1,
    "pid": 9084,
    "index": 25
  },
  {
    "name": "Require(23) node_modules/egg/config/config.local.js",
    "start": 1586523635240,
    "end": 1586523635240,
    "duration": 0,
    "pid": 9084,
    "index": 26
  },
  {
    "name": "Load extend/application.js",
    "start": 1586523635242,
    "end": 1586523635419,
    "duration": 177,
    "pid": 9084,
    "index": 27
  },
  {
    "name": "Require(24) node_modules/egg-session/app/extend/application.js",
    "start": 1586523635244,
    "end": 1586523635245,
    "duration": 1,
    "pid": 9084,
    "index": 28
  },
  {
    "name": "Require(25) node_modules/egg-security/app/extend/application.js",
    "start": 1586523635247,
    "end": 1586523635250,
    "duration": 3,
    "pid": 9084,
    "index": 29
  },
  {
    "name": "Require(26) node_modules/egg-jsonp/app/extend/application.js",
    "start": 1586523635252,
    "end": 1586523635257,
    "duration": 5,
    "pid": 9084,
    "index": 30
  },
  {
    "name": "Require(27) node_modules/egg-logrotator/app/extend/application.js",
    "start": 1586523635262,
    "end": 1586523635268,
    "duration": 6,
    "pid": 9084,
    "index": 31
  },
  {
    "name": "Require(28) node_modules/egg-view/app/extend/application.js",
    "start": 1586523635271,
    "end": 1586523635275,
    "duration": 4,
    "pid": 9084,
    "index": 32
  },
  {
    "name": "Require(29) node_modules/egg-jwt/app/extend/application.js",
    "start": 1586523635278,
    "end": 1586523635404,
    "duration": 126,
    "pid": 9084,
    "index": 33
  },
  {
    "name": "Load extend/request.js",
    "start": 1586523635419,
    "end": 1586523635453,
    "duration": 34,
    "pid": 9084,
    "index": 34
  },
  {
    "name": "Require(30) node_modules/egg/app/extend/request.js",
    "start": 1586523635437,
    "end": 1586523635440,
    "duration": 3,
    "pid": 9084,
    "index": 35
  },
  {
    "name": "Load extend/response.js",
    "start": 1586523635453,
    "end": 1586523635487,
    "duration": 34,
    "pid": 9084,
    "index": 36
  },
  {
    "name": "Require(31) node_modules/egg/app/extend/response.js",
    "start": 1586523635467,
    "end": 1586523635473,
    "duration": 6,
    "pid": 9084,
    "index": 37
  },
  {
    "name": "Load extend/context.js",
    "start": 1586523635487,
    "end": 1586523635674,
    "duration": 187,
    "pid": 9084,
    "index": 38
  },
  {
    "name": "Require(32) node_modules/egg-security/app/extend/context.js",
    "start": 1586523635488,
    "end": 1586523635530,
    "duration": 42,
    "pid": 9084,
    "index": 39
  },
  {
    "name": "Require(33) node_modules/egg-jsonp/app/extend/context.js",
    "start": 1586523635531,
    "end": 1586523635536,
    "duration": 5,
    "pid": 9084,
    "index": 40
  },
  {
    "name": "Require(34) node_modules/egg-i18n/app/extend/context.js",
    "start": 1586523635538,
    "end": 1586523635539,
    "duration": 1,
    "pid": 9084,
    "index": 41
  },
  {
    "name": "Require(35) node_modules/egg-multipart/app/extend/context.js",
    "start": 1586523635542,
    "end": 1586523635641,
    "duration": 99,
    "pid": 9084,
    "index": 42
  },
  {
    "name": "Require(36) node_modules/egg-view/app/extend/context.js",
    "start": 1586523635644,
    "end": 1586523635648,
    "duration": 4,
    "pid": 9084,
    "index": 43
  },
  {
    "name": "Require(37) node_modules/egg-mongoose/app/extend/context.js",
    "start": 1586523635650,
    "end": 1586523635650,
    "duration": 0,
    "pid": 9084,
    "index": 44
  },
  {
    "name": "Require(38) node_modules/egg/app/extend/context.js",
    "start": 1586523635653,
    "end": 1586523635660,
    "duration": 7,
    "pid": 9084,
    "index": 45
  },
  {
    "name": "Load extend/helper.js",
    "start": 1586523635674,
    "end": 1586523635754,
    "duration": 80,
    "pid": 9084,
    "index": 46
  },
  {
    "name": "Require(39) node_modules/egg-security/app/extend/helper.js",
    "start": 1586523635675,
    "end": 1586523635725,
    "duration": 50,
    "pid": 9084,
    "index": 47
  },
  {
    "name": "Require(40) node_modules/egg/app/extend/helper.js",
    "start": 1586523635738,
    "end": 1586523635739,
    "duration": 1,
    "pid": 9084,
    "index": 48
  },
  {
    "name": "Load app.js",
    "start": 1586523635755,
    "end": 1586523635892,
    "duration": 137,
    "pid": 9084,
    "index": 49
  },
  {
    "name": "Require(41) node_modules/egg-session/app.js",
    "start": 1586523635756,
    "end": 1586523635758,
    "duration": 2,
    "pid": 9084,
    "index": 50
  },
  {
    "name": "Require(42) node_modules/egg-security/app.js",
    "start": 1586523635759,
    "end": 1586523635766,
    "duration": 7,
    "pid": 9084,
    "index": 51
  },
  {
    "name": "Require(43) node_modules/egg-onerror/app.js",
    "start": 1586523635769,
    "end": 1586523635796,
    "duration": 27,
    "pid": 9084,
    "index": 52
  },
  {
    "name": "Require(44) node_modules/egg-i18n/app.js",
    "start": 1586523635797,
    "end": 1586523635845,
    "duration": 48,
    "pid": 9084,
    "index": 53
  },
  {
    "name": "Require(45) node_modules/egg-watcher/app.js",
    "start": 1586523635846,
    "end": 1586523635859,
    "duration": 13,
    "pid": 9084,
    "index": 54
  },
  {
    "name": "Require(46) node_modules/egg-schedule/app.js",
    "start": 1586523635860,
    "end": 1586523635866,
    "duration": 6,
    "pid": 9084,
    "index": 55
  },
  {
    "name": "Require(47) node_modules/egg-multipart/app.js",
    "start": 1586523635867,
    "end": 1586523635875,
    "duration": 8,
    "pid": 9084,
    "index": 56
  },
  {
    "name": "Require(48) node_modules/egg-development/app.js",
    "start": 1586523635876,
    "end": 1586523635876,
    "duration": 0,
    "pid": 9084,
    "index": 57
  },
  {
    "name": "Require(49) node_modules/egg-logrotator/app.js",
    "start": 1586523635877,
    "end": 1586523635878,
    "duration": 1,
    "pid": 9084,
    "index": 58
  },
  {
    "name": "Require(50) node_modules/egg-static/app.js",
    "start": 1586523635879,
    "end": 1586523635879,
    "duration": 0,
    "pid": 9084,
    "index": 59
  },
  {
    "name": "Require(51) node_modules/egg-view-ejs/app.js",
    "start": 1586523635882,
    "end": 1586523635882,
    "duration": 0,
    "pid": 9084,
    "index": 60
  },
  {
    "name": "Require(52) node_modules/egg-mongoose/app.js",
    "start": 1586523635883,
    "end": 1586523635884,
    "duration": 1,
    "pid": 9084,
    "index": 61
  },
  {
    "name": "Require(53) node_modules/egg-jwt/app.js",
    "start": 1586523635885,
    "end": 1586523635886,
    "duration": 1,
    "pid": 9084,
    "index": 62
  },
  {
    "name": "Require(54) node_modules/egg-cors/app.js",
    "start": 1586523635887,
    "end": 1586523635888,
    "duration": 1,
    "pid": 9084,
    "index": 63
  },
  {
    "name": "Before Start in node_modules/egg-watcher/lib/init.js:15:14",
    "start": 1586523635913,
    "end": 1586523637858,
    "duration": 1945,
    "pid": 9084,
    "index": 64
  },
  {
    "name": "Before Start in node_modules/egg-mongoose/lib/mongoose.js:91:7",
    "start": 1586523637288,
    "end": 1586523638122,
    "duration": 834,
    "pid": 9084,
    "index": 65
  },
  {
    "name": "Before Start in node_modules/egg-mongoose/lib/mongoose.js:49:9",
    "start": 1586523637289,
    "end": 1586523637838,
    "duration": 549,
    "pid": 9084,
    "index": 66
  },
  {
    "name": "Load Service",
    "start": 1586523637289,
    "end": 1586523637392,
    "duration": 103,
    "pid": 9084,
    "index": 67
  },
  {
    "name": "Load \"service\" to Context",
    "start": 1586523637289,
    "end": 1586523637392,
    "duration": 103,
    "pid": 9084,
    "index": 68
  },
  {
    "name": "Load Middleware",
    "start": 1586523637392,
    "end": 1586523637692,
    "duration": 300,
    "pid": 9084,
    "index": 69
  },
  {
    "name": "Load \"middlewares\" to Application",
    "start": 1586523637392,
    "end": 1586523637670,
    "duration": 278,
    "pid": 9084,
    "index": 70
  },
  {
    "name": "Load Controller",
    "start": 1586523637692,
    "end": 1586523637718,
    "duration": 26,
    "pid": 9084,
    "index": 71
  },
  {
    "name": "Load \"controller\" to Application",
    "start": 1586523637692,
    "end": 1586523637718,
    "duration": 26,
    "pid": 9084,
    "index": 72
  },
  {
    "name": "Load Router",
    "start": 1586523637718,
    "end": 1586523637727,
    "duration": 9,
    "pid": 9084,
    "index": 73
  },
  {
    "name": "Require(55) app/router.js",
    "start": 1586523637719,
    "end": 1586523637720,
    "duration": 1,
    "pid": 9084,
    "index": 74
  },
  {
    "name": "Before Start in node_modules/egg-core/lib/egg.js:303:10",
    "start": 1586523637721,
    "end": 1586523637838,
    "duration": 117,
    "pid": 9084,
    "index": 75
  },
  {
    "name": "Load \"model\" to Application",
    "start": 1586523637745,
    "end": 1586523637837,
    "duration": 92,
    "pid": 9084,
    "index": 76
  }
]